{
  "UnitInfo": {
    "Name": "Blade Dancer",
    "Rarity": "Legendary",
    "Faction": "Forest Alliance",
    "UnitType": "Damage",
    "Target": "First",
    "Arena": 11,
    "AoE": "No",
    "Lv": [
      7,
      15
    ],
    "Mana Lv": [
      1,
      5
    ],
    "Merge Rank": [
      1,
      7
    ],
    "Attributes": 6
  },
  "Levels": {
    "7": {
      "Damage": 0,
      "Attack Interval": 0,
      "Minimum boost": 0,
      "Maximum boost": 0,
      "Attack speed increase": 0,
      "Hero cooldown": 0
    },
    "8": {
      "Damage": 55,
      "Attack Interval": 0,
      "Minimum boost": 0,
      "Maximum boost": 0,
      "Attack speed increase": 0,
      "Hero cooldown": 0.5
    },
    "9": {
      "Damage": 121,
      "Attack Interval": 0,
      "Minimum boost": 0,
      "Maximum boost": 0,
      "Attack speed increase": 0,
      "Hero cooldown": 1
    },
    "10": {
      "Damage": 200,
      "Attack Interval": 0,
      "Minimum boost": 0,
      "Maximum boost": 0,
      "Attack speed increase": 0,
      "Hero cooldown": 1.5
    },
    "11": {
      "Damage": 295,
      "Attack Interval": 0,
      "Minimum boost": 0,
      "Maximum boost": 0,
      "Attack speed increase": 0,
      "Hero cooldown": 2
    },
    "12": {
      "Damage": 409,
      "Attack Interval": 0,
      "Minimum boost": 0,
      "Maximum boost": 0,
      "Attack speed increase": 0,
      "Hero cooldown": 2.5
    },
    "13": {
      "Damage": 546,
      "Attack Interval": 0,
      "Minimum boost": 0,
      "Maximum boost": 0,
      "Attack speed increase": 0,
      "Hero cooldown": 3
    },
    "14": {
      "Damage": 711,
      "Attack Interval": 0,
      "Minimum boost": 0,
      "Maximum boost": 0,
      "Attack speed increase": 0,
      "Hero cooldown": 3.5
    },
    "15": {
      "Damage": 908,
      "Attack Interval": 0,
      "Minimum boost": 0,
      "Maximum boost": 0,
      "Attack speed increase": 0,
      "Hero cooldown": 4
    },
    "Base": {
      "Damage": 275,
      "Attack Interval": 1,
      "Minimum boost": 2,
      "Maximum boost": 4.5,
      "Attack speed increase": 1.5,
      "Hero cooldown": 4
    }
  },
  "ManaLevels": {
    "1": {
      "Damage": 0
    },
    "2": {
      "Damage": 75
    },
    "3": {
      "Damage": 150
    },
    "4": {
      "Damage": 225
    },
    "5": {
      "Damage": 300
    },
    "Base": {
      "Damage": 275,
      "Attack Interval": 1,
      "Minimum boost": 2,
      "Maximum boost": 4.5,
      "Attack speed increase": 1.5,
      "Hero cooldown": 4
    }
  },
  "MergeRanks": {
    "1": {
      "Attack Interval": 0
    },
    "2": {
      "Attack Interval": -0.5
    },
    "3": {
      "Attack Interval": -0.67
    },
    "4": {
      "Attack Interval": -0.75
    },
    "5": {
      "Attack Interval": -0.8
    },
    "6": {
      "Attack Interval": -0.83
    },
    "7": {
      "Attack Interval": -0.86
    },
    "Base": {
      "Damage": 275,
      "Attack Interval": 1,
      "Minimum boost": 2,
      "Maximum boost": 4.5,
      "Attack speed increase": 1.5,
      "Hero cooldown": 4
    }
  },
  "SpecialAbilities": {}
}